sphinx_csv_tools/__init__.py
sphinx_csv_tools/csv.py
sphinx_csv_tools-0.2.dist-info/LICENSE
sphinx_csv_tools-0.2.dist-info/METADATA
sphinx_csv_tools-0.2.dist-info/WHEEL
sphinx_csv_tools-0.2.dist-info/top_level.txt
sphinx_csv_tools-0.2.dist-info/RECORD
