Metadata-Version: 2.1
Name: sphinx-csv-tools
Version: 0.2
Summary: Sphinx CSV tools extension
Home-page: https://github.com/Nefti-sama/sphinx-csv-tools
Author: Nefti
Author-email: nefti.code@gmail.com
License: Apache License 2.0
Keywords: sphinx csv tools
Platform: any
Classifier: Development Status :: 4 - Beta
Classifier: Intended Audience :: Developers
Classifier: License :: OSI Approved :: Apache Software License
Classifier: Operating System :: OS Independent
Classifier: Programming Language :: Python
Classifier: Programming Language :: Python :: 3
Classifier: Programming Language :: Python :: 3.8
Classifier: Programming Language :: Python :: 3.9
Classifier: Programming Language :: Python :: 3.10
Classifier: Programming Language :: Python :: Implementation :: CPython
Classifier: Topic :: Database
Requires-Python: >=3.8
Requires-Dist: sphinx
Provides-Extra: development
Requires-Dist: setuptools ; extra == 'development'
Requires-Dist: twine ; extra == 'development'
Requires-Dist: wheel ; extra == 'development'
Provides-Extra: testing
Requires-Dist: flake8 ; extra == 'testing'
Requires-Dist: pytest ; extra == 'testing'
Requires-Dist: pytest-flake8 ; extra == 'testing'
Requires-Dist: pytest-isort ; extra == 'testing'
